odoo/addons/mail_debrand/README.rst
odoo/addons/mail_debrand/__init__.py
odoo/addons/mail_debrand/__manifest__.py
odoo/addons/mail_debrand/i18n/de.po
odoo/addons/mail_debrand/i18n/es.po
odoo/addons/mail_debrand/i18n/fr.po
odoo/addons/mail_debrand/i18n/fr_FR.po
odoo/addons/mail_debrand/i18n/it.po
odoo/addons/mail_debrand/i18n/mail_debrand.pot
odoo/addons/mail_debrand/i18n/nl.po
odoo/addons/mail_debrand/i18n/pt.po
odoo/addons/mail_debrand/i18n/sl.po
odoo/addons/mail_debrand/i18n/sr_Latn.po
odoo/addons/mail_debrand/i18n/sv.po
odoo/addons/mail_debrand/i18n/tr.po
odoo/addons/mail_debrand/models/__init__.py
odoo/addons/mail_debrand/models/mail_mail.py
odoo/addons/mail_debrand/models/mail_render_mixin.py
odoo/addons/mail_debrand/readme/CONTRIBUTORS.md
odoo/addons/mail_debrand/readme/DESCRIPTION.md
odoo/addons/mail_debrand/readme/HISTORY.md
odoo/addons/mail_debrand/readme/ROADMAP.md
odoo/addons/mail_debrand/readme/USAGE.md
odoo/addons/mail_debrand/static/description/icon.png
odoo/addons/mail_debrand/static/description/icon.svg
odoo/addons/mail_debrand/static/description/index.html
odoo/addons/mail_debrand/tests/__init__.py
odoo/addons/mail_debrand/tests/test_mail_debrand.py
odoo/addons/mail_debrand/tests/test_mail_debrand_digest.py
odoo/addons/mail_debrand/tests/test_mail_debrand_signup.py
odoo_addon_mail_debrand-18.0.1.0.1.3.dist-info/METADATA
odoo_addon_mail_debrand-18.0.1.0.1.3.dist-info/WHEEL
odoo_addon_mail_debrand-18.0.1.0.1.3.dist-info/top_level.txt
odoo_addon_mail_debrand-18.0.1.0.1.3.dist-info/RECORD
